Metadata-Version: 2.1
Name: discord.py-message-components
Version: 1.7.5.4
Summary: The discord.py Library with implementation of the Discord-Message-Components
Home-page: https://github.com/mccoderpy/discord.py-message-components
Author: mccoder.py
Author-email: mccuber04@outlook.de
License: MIT
Project-URL: Documentation, https://discordpy-message-components.readthedocs.io/en/latest/
Project-URL: Source, https://github.com/mccoderpy/discord.py-message-components/
Project-URL: Support, https://discord.gg/sb69muSqsg
Project-URL: Issue Tracker, https://github.com/mccoderpy/discord.py-message-components/issues
Keywords: discord.py discord.py-message-components discord-components discord-interactions discord message-components
Platform: UNKNOWN
Classifier: Development Status :: 4 - Beta
Classifier: License :: OSI Approved :: MIT License
Classifier: Intended Audience :: Developers
Classifier: Natural Language :: English
Classifier: Operating System :: OS Independent
Classifier: Programming Language :: Python :: 3.5
Classifier: Programming Language :: Python :: 3.6
Classifier: Programming Language :: Python :: 3.7
Classifier: Programming Language :: Python :: 3.8
Classifier: Programming Language :: Python :: 3.9
Classifier: Topic :: Internet
Classifier: Topic :: Software Development :: Libraries
Classifier: Topic :: Software Development :: Libraries :: Python Modules
Classifier: Topic :: Utilities
Requires-Python: >=3.6
License-File: LICENSE
Requires-Dist: aiohttp
Requires-Dist: chardet
Requires-Dist: yarl
Requires-Dist: async-timeout
Requires-Dist: typing-extensions
Requires-Dist: attrs
Requires-Dist: multidict
Requires-Dist: idna
Provides-Extra: docs
Requires-Dist: sphinx (==3.0.3) ; extra == 'docs'
Requires-Dist: sphinxcontrib-trio (==1.1.2) ; extra == 'docs'
Requires-Dist: sphinxcontrib-websupport ; extra == 'docs'
Provides-Extra: voice
Requires-Dist: PyNaCl (<1.5,>=1.3.0) ; extra == 'voice'
